{
  "source": "QUL (Quranic Universal Library)",
  "source_url": "https://qul.tarteel.ai/resources/quran-metadata/bb52e39dd308a24e8aa10a40d7780d58/download",
  "source_id": 67,
  "category": "quran-metadata",
  "title": "Hizb",
  "sha256": "890c3aecccd8840d2d7724975157eefe1a12d8e8c790b933dc84bea43c00a601",
  "downloaded_at": "2026-05-05T20:50:35Z",
  "license_tag": "factual",
  "license_chip": "",
  "tags": "",
  "attribution_required": true,
  "notes": "",
  "attribution_text": "Hizb (via QUL — Tarteel AI)",
  "license_classified_at": "2026-05-05T21:08:09+00:00",
  "license_auto_tagged": true
}