{
  "source": "QUL (Quranic Universal Library)",
  "source_url": "https://qul.tarteel.ai/resources/quran-metadata/9d470ef5b8aaabea06af7772b71b00d8/download",
  "source_id": 67,
  "category": "quran-metadata",
  "title": "Hizb",
  "sha256": "9e513bbab1ec1b77aad05be29836b6dd4adf81483756021aeff1d66ada015d22",
  "downloaded_at": "2026-05-05T20:50:34Z",
  "license_tag": "factual",
  "license_chip": "",
  "tags": "",
  "attribution_required": true,
  "notes": "",
  "attribution_text": "Hizb (via QUL — Tarteel AI)",
  "license_classified_at": "2026-05-05T21:08:09+00:00",
  "license_auto_tagged": true
}