{
  "source": "QUL (Quranic Universal Library)",
  "source_url": "https://qul.tarteel.ai/resources/tafsir/42da9ed90e70da9d2361e43b52144ad4/download",
  "source_id": 266,
  "category": "tafsir",
  "title": "English Al-Mukhtasar",
  "sha256": "bac32384ee752fb11e0e66f9d7071ae752e809147af49aac013668b06e443f12",
  "downloaded_at": "2026-05-05T20:51:05Z",
  "license_tag": "permissive-with-credit",
  "license_chip": "",
  "tags": "",
  "attribution_required": true,
  "notes": "",
  "attribution_text": "English Al-Mukhtasar (via QUL — Tarteel AI)",
  "license_classified_at": "2026-05-05T21:08:08+00:00",
  "license_auto_tagged": true
}