{
  "source": "QUL (Quranic Universal Library)",
  "source_url": "https://qul.tarteel.ai/resources/tafsir/342e14568d1e68245cacc1f4a97a567e/download",
  "source_id": 29,
  "category": "tafsir",
  "title": "Tafsir Bayan ul Quran",
  "sha256": "2db70609ac06880c45942184d5b2a62493d7ba64c7c2c2ff2338341a1471cbbb",
  "downloaded_at": "2026-05-05T20:51:33Z",
  "license_tag": "permissive-with-credit",
  "license_chip": "",
  "tags": "",
  "attribution_required": true,
  "notes": "",
  "attribution_text": "Tafsir Bayan ul Quran (via QUL — Tarteel AI)",
  "license_classified_at": "2026-05-05T21:08:08+00:00",
  "license_auto_tagged": true
}