{
  "source": "QUL (Quranic Universal Library)",
  "source_url": "https://qul.tarteel.ai/resources/tafsir/847b65e7d7006fd4a475ab550f2af317/download",
  "source_id": 34,
  "category": "tafsir",
  "title": "Maarif-ul-Quran",
  "sha256": "2e42a7bf2ebb770f1352764dfbf48c84d90918e1dd4ec0d806f9f4c4ffce1b64",
  "downloaded_at": "2026-05-05T20:51:37Z",
  "license_tag": "permissive-with-credit",
  "license_chip": "",
  "tags": "",
  "attribution_required": true,
  "notes": "",
  "attribution_text": "Maarif-ul-Quran (via QUL — Tarteel AI)",
  "license_classified_at": "2026-05-05T21:08:08+00:00",
  "license_auto_tagged": true
}